cubicweb_vtimeline/__init__.py
cubicweb_vtimeline/__pkginfo__.py
cubicweb_vtimeline/views.py
cubicweb_vtimeline/data/veritejs/css/blank.gif
cubicweb_vtimeline/data/veritejs/css/fancybox_sprite.png
cubicweb_vtimeline/data/veritejs/css/fancybox_sprite@2x.png
cubicweb_vtimeline/data/veritejs/css/loading.gif
cubicweb_vtimeline/data/veritejs/css/timeline.css
cubicweb_vtimeline/data/veritejs/css/timeline.png
cubicweb_vtimeline/data/veritejs/css/timeline@2x.png
cubicweb_vtimeline/data/veritejs/css/themes/dark.css
cubicweb_vtimeline/data/veritejs/css/themes/timeline-dark.png
cubicweb_vtimeline/data/veritejs/css/themes/timeline-dark@2x.png
cubicweb_vtimeline/data/veritejs/css/themes/timeline-texture.png
cubicweb_vtimeline/data/veritejs/css/themes/font/AbrilFatface-Average.css
cubicweb_vtimeline/data/veritejs/css/themes/font/Arvo-PTSans.css
cubicweb_vtimeline/data/veritejs/css/themes/font/Bevan-PotanoSans.css
cubicweb_vtimeline/data/veritejs/css/themes/font/BreeSerif-OpenSans.css
cubicweb_vtimeline/data/veritejs/css/themes/font/DroidSerif-DroidSans.css
cubicweb_vtimeline/data/veritejs/css/themes/font/Georgia-Helvetica.css
cubicweb_vtimeline/data/veritejs/css/themes/font/Lekton-Molengo.css
cubicweb_vtimeline/data/veritejs/css/themes/font/Lora-Istok.css
cubicweb_vtimeline/data/veritejs/css/themes/font/Merriweather-NewsCycle.css
cubicweb_vtimeline/data/veritejs/css/themes/font/NewsCycle-Merriweather.css
cubicweb_vtimeline/data/veritejs/css/themes/font/NixieOne-Ledger.css
cubicweb_vtimeline/data/veritejs/css/themes/font/PT.css
cubicweb_vtimeline/data/veritejs/css/themes/font/PTSerif-PTSans.css
cubicweb_vtimeline/data/veritejs/css/themes/font/Pacifico-Arimo.css
cubicweb_vtimeline/data/veritejs/css/themes/font/PlayfairDisplay-Muli.css
cubicweb_vtimeline/data/veritejs/css/themes/font/PoiretOne-Molengo.css
cubicweb_vtimeline/data/veritejs/css/themes/font/Rancho-Gudea.css
cubicweb_vtimeline/data/veritejs/css/themes/font/SansitaOne-Kameron.css
cubicweb_vtimeline-1.0.0.dist-info/METADATA
cubicweb_vtimeline-1.0.0.dist-info/WHEEL
cubicweb_vtimeline-1.0.0.dist-info/entry_points.txt
cubicweb_vtimeline-1.0.0.dist-info/top_level.txt
cubicweb_vtimeline-1.0.0.dist-info/RECORD
