Metadata-Version: 2.4
Name: cubicweb-vtimeline
Version: 1.0.0
Summary: VeriteCo / TimelineJS cube
Home-page: https://forge.extranet.logilab.fr/cubicweb/cubes/cubicweb-vtimeline
Author: LOGILAB S.A. (Paris, FRANCE)
Author-email: contact@logilab.fr
License: LGPL
Classifier: Environment :: Web Environment
Classifier: Framework :: CubicWeb
Classifier: Programming Language :: Python
Classifier: Programming Language :: JavaScript
Requires-Dist: cubicweb<5.0.0,>=4.0.0
Dynamic: author
Dynamic: author-email
Dynamic: classifier
Dynamic: description
Dynamic: home-page
Dynamic: license
Dynamic: requires-dist
Dynamic: summary
